// converted by version 1.3
// on Thu Mar 27 21:29:48 ICT 2014

.package test {
	.aid 0x1:0x2:0x3:0x4:0x5:0x6:0x7:0x8:0x9:0x0;
	.version 1.0;

	.imports {
		0xA0:0x0:0x0:0x0:0x62:0x1:0x1 1.3;		//javacard/framework
		0xA0:0x0:0x0:0x0:0x62:0x0:0x1 1.0;		//java/lang
	}

	.applet {
		0x1:0x2:0x3:0x4:0x5:0x6:0x7:0x8:0x9:0x0:0x0 TestApplet;
	}

	.constantPool {
		// 0
		staticMethodRef 0.3.0()V;		// javacard/framework/Applet.<init>()V
		// 1
		staticFieldRef byte[] TestApplet/memory;
		// 2
		classRef 0.9;		// javacard/framework/OwnerPIN
		// 3
		staticMethodRef 0.9.0(BB)V;		// javacard/framework/OwnerPIN.<init>(BB)V
		// 4
		staticFieldRef 0.9 TestApplet/pin;
		// 5
		staticFieldRef byte[] TestApplet/DEFAULT_PIN;
		// 6
		virtualMethodRef 0.9.8([BSB)V;		// update([BSB)V
		// 7
		classRef TestApplet;
		// 8
		staticMethodRef TestApplet/<init>()V;
		// 9
		virtualMethodRef 0.3.1()V;		// register()V
		// 10
		virtualMethodRef 0.10.1()[B;		// getBuffer()[B
		// 11
		staticMethodRef TestApplet/cmdSELECT(Ljavacard/framework/APDU;)V;
			.descriptor	Ljavacard/framework/APDU;	0.10;

		// 12
		staticMethodRef TestApplet/cmdVERIFY(Ljavacard/framework/APDU;)V;
			.descriptor	Ljavacard/framework/APDU;	0.10;

		// 13
		staticMethodRef TestApplet/cmdPUTDATA(Ljavacard/framework/APDU;)V;
			.descriptor	Ljavacard/framework/APDU;	0.10;

		// 14
		staticMethodRef TestApplet/cmdGETDATA(Ljavacard/framework/APDU;)V;
			.descriptor	Ljavacard/framework/APDU;	0.10;

		// 15
		staticMethodRef 0.7.1(S)V;		// javacard/framework/ISOException.throwIt(S)V
		// 16
		staticMethodRef TestApplet/cmdDELETE(Ljavacard/framework/APDU;)V;
			.descriptor	Ljavacard/framework/APDU;	0.10;

		// 17
		virtualMethodRef TestApplet/receiveAPDUBody(Ljavacard/framework/APDU;)V;
			.descriptor	Ljavacard/framework/APDU;	0.10;

		// 18
		staticMethodRef 0.8.3()Ljavacard/framework/AID;;		// javacard/framework/JCSystem.getAID()Ljavacard/framework/AID;
			.descriptor	Ljavacard/framework/AID;	0.6;

		// 19
		virtualMethodRef 0.6.2([BSB)Z;		// equals([BSB)Z
		// 20
		virtualMethodRef 0.9.1([BSB)Z;		// check([BSB)Z
		// 21
		virtualMethodRef 0.9.2()B;		// getTriesRemaining()B
		// 22
		virtualMethodRef 0.9.4()Z;		// isValidated()Z
		// 23
		virtualMethodRef TestApplet/SetDO(SSLjavacard/framework/APDU;)S;
			.descriptor	Ljavacard/framework/APDU;	0.10;

		// 24
		virtualMethodRef TestApplet/GetIdxToDO(S)S;
		// 25
		virtualMethodRef 0.10.7()S;		// setOutgoing()S
		// 26
		virtualMethodRef 0.10.9(S)V;		// setOutgoingLength(S)V
		// 27
		virtualMethodRef 0.10.5([BSS)V;		// sendBytesLong([BSS)V
		// 28
		staticMethodRef 0.16.3([BSSB)S;		// javacard/framework/Util.arrayFillNonAtomic([BSSB)S
		// 29
		staticFieldRef short TestApplet/memory_NoOfDOs;
		// 30
		virtualMethodRef 0.10.6()S;		// setIncomingAndReceive()S
		// 31
		virtualMethodRef TestApplet/GetIdxToFreeSpace()S;
		// 32
		staticMethodRef 0.16.1([BS[BSS)S;		// javacard/framework/Util.arrayCopy([BS[BSS)S
	}

	.class public TestApplet 0 extends 0.3 {		// extends javacard/framework/Applet

		.fields {
			static final byte PROP_CLASS = -128;		// B
			static final byte INS_SELECT = -92;		// B
			static final byte INS_VERIFY = 32;		// B
			static final byte INS_PUTDATA = -38;		// B
			static final byte INS_GETDATA = -54;		// B
			static final byte INS_DELETE = 6;		// B
			static final short SW_PIN_FAILED = 25536;		// S
			static final short SW_DATA_NOT_FOUND = 27272;		// S
			static final short SIZE_MEMORY = 9;		// S
			static byte[] memory;		// [B
			static short memory_NoOfDOs;		// S
			static final short LEN_TAG = 1;		// S
			static final short LEN_LEN = 1;		// S
			static final byte[] DEFAULT_PIN = {18,52};		// [B
			static final byte PIN_SIZE = 2;		// B
			static final byte DEFAULT_PIN_MAXEC = 3;		// B
			static final byte PIN_ID = 1;		// B
			static 0.9 pin;		// Ljavacard/framework/OwnerPIN;
			private static final short DO_PROPPER_SET = 10;		// S
			private static final short NOT_ENOUGH_SPACE = 11;		// S
			private static final short DO_HAVE_WRONG_LENGTH = 12;		// S
			private static final short DO_NOT_FOUND = 13;		// S
		}

		.publicMethodTable 7 {
			equals(Ljava/lang/Object;)Z;
			register()V;
			register([BSB)V;
			selectingApplet()Z;
			deselect()V;
			getShareableInterfaceObject(Ljavacard/framework/AID;B)Ljavacard/framework/Shareable;;
			select()Z;
			process(Ljavacard/framework/APDU;)V;
			receiveAPDUBody(Ljavacard/framework/APDU;)V;
			GetIdxToFreeSpace()S;
			GetIdxToDO(S)S;
			SetDO(SSLjavacard/framework/APDU;)S;
		}

		.packageMethodTable 0 {
		}

		.method public <init>()V 0 {
			.stack 1;
			.locals 0;

				L0:	aload_0;
					invokespecial 0;		// javacard/framework/Applet.<init>()V
					return;
		}

		.method public static install([BSB)V 1 {
			.stack 4;
			.locals 0;

				L0:	bspush 9;
					newarray 11;
					putstatic_a 1;		// reference test/TestApplet.memory
					new 2;		// javacard/framework/OwnerPIN
					dup;
					sconst_3;
					sconst_2;
					invokespecial 3;		// javacard/framework/OwnerPIN.<init>(BB)V
					putstatic_a 4;		// reference test/TestApplet.pin
					getstatic_a 4;		// reference test/TestApplet.pin
					getstatic_a 5;		// reference test/TestApplet.DEFAULT_PIN
					sconst_0;
					sconst_2;
					invokevirtual 6;		// update([BSB)V
					new 7;		// test/TestApplet
					dup;
					invokespecial 8;		// test/TestApplet.<init>()V
					invokevirtual 9;		// register()V
					return;
		}

		.method public process(Ljavacard/framework/APDU;)V 7 {
			.stack 2;
			.locals 1;

			.descriptor	Ljavacard/framework/APDU;	0.10;

				L0:	aload_1;
					invokevirtual 10;		// getBuffer()[B
					astore_2;
					aload_2;
					sconst_0;
					baload;
					ifne L7;
				L1:	aload_2;
					sconst_1;
					baload;
					slookupswitch L6 4 -92 L2 -54 L5 -38 L4 32 L3;
				L2:	aload_0;
					aload_1;
					invokespecial 11;		// test/TestApplet.cmdSELECT(Ljavacard/framework/APDU;)V
					goto L12;
				L3:	aload_0;
					aload_1;
					invokespecial 12;		// test/TestApplet.cmdVERIFY(Ljavacard/framework/APDU;)V
					goto L12;
				L4:	aload_0;
					aload_1;
					invokespecial 13;		// test/TestApplet.cmdPUTDATA(Ljavacard/framework/APDU;)V
					goto L12;
				L5:	aload_0;
					aload_1;
					invokespecial 14;		// test/TestApplet.cmdGETDATA(Ljavacard/framework/APDU;)V
					goto L12;
				L6:	sspush 27904;
					invokestatic 15;		// javacard/framework/ISOException.throwIt(S)V
					goto L12;
				L7:	aload_2;
					sconst_0;
					baload;
					bspush -128;
					if_scmpne L11;
				L8:	aload_2;
					sconst_1;
					baload;
					stableswitch L10 6 6 L9;
				L9:	aload_0;
					aload_1;
					invokespecial 16;		// test/TestApplet.cmdDELETE(Ljavacard/framework/APDU;)V
					goto L12;
				L10:	sspush 27904;
					invokestatic 15;		// javacard/framework/ISOException.throwIt(S)V
					goto L12;
				L11:	sspush 28160;
					invokestatic 15;		// javacard/framework/ISOException.throwIt(S)V
				L12:	return;
		}

		.method private cmdSELECT(Ljavacard/framework/APDU;)V {
			.stack 4;
			.locals 2;

			.descriptor	Ljavacard/framework/APDU;	0.10;

				L0:	aload_1;
					invokevirtual 10;		// getBuffer()[B
					astore_2;
					aload_2;
					sconst_2;
					baload;
					sconst_4;
					if_scmpeq L2;
				L1:	sspush 27392;
					invokestatic 15;		// javacard/framework/ISOException.throwIt(S)V
				L2:	aload_2;
					sconst_3;
					baload;
					ifeq L4;
				L3:	sspush 27392;
					invokestatic 15;		// javacard/framework/ISOException.throwIt(S)V
				L4:	aload_2;
					sconst_4;
					baload;
					sspush 255;
					sand;
					sstore_3;
					aload_0;
					aload_1;
					invokevirtual 17;		// receiveAPDUBody(Ljavacard/framework/APDU;)V
					invokestatic 18;		// javacard/framework/JCSystem.getAID()Ljavacard/framework/AID;
					aload_2;
					sconst_5;
					sload_3;
					s2b;
					invokevirtual 19;		// equals([BSB)Z
					ifne L6;
				L5:	sspush 27033;
					invokestatic 15;		// javacard/framework/ISOException.throwIt(S)V
				L6:	sspush -28672;
					invokestatic 15;		// javacard/framework/ISOException.throwIt(S)V
					return;
		}

		.method private cmdVERIFY(Ljavacard/framework/APDU;)V {
			.stack 4;
			.locals 3;

			.descriptor	Ljavacard/framework/APDU;	0.10;

				L0:	aload_1;
					invokevirtual 10;		// getBuffer()[B
					astore_2;
					aload_2;
					sconst_2;
					baload;
					ifeq L2;
				L1:	sspush 27392;
					invokestatic 15;		// javacard/framework/ISOException.throwIt(S)V
				L2:	aload_2;
					sconst_4;
					baload;
					sspush 255;
					sand;
					sstore_3;
					aload_0;
					aload_1;
					invokevirtual 17;		// receiveAPDUBody(Ljavacard/framework/APDU;)V
					aload_2;
					sconst_3;
					baload;
					sconst_1;
					if_scmpne L7;
				L3:	sload_3;
					sconst_2;
					if_scmpeq L5;
				L4:	sspush 26368;
					invokestatic 15;		// javacard/framework/ISOException.throwIt(S)V
				L5:	getstatic_a 4;		// reference test/TestApplet.pin
					aload_2;
					sconst_5;
					sconst_2;
					invokevirtual 20;		// check([BSB)Z
					ifne L8;
				L6:	getstatic_a 4;		// reference test/TestApplet.pin
					invokevirtual 21;		// getTriesRemaining()B
					sstore 4;
					sspush 25536;
					sload 4;
					sadd;
					invokestatic 15;		// javacard/framework/ISOException.throwIt(S)V
					goto L8;
				L7:	sspush 27392;
					invokestatic 15;		// javacard/framework/ISOException.throwIt(S)V
				L8:	sspush -28672;
					invokestatic 15;		// javacard/framework/ISOException.throwIt(S)V
					return;
		}

		.method private cmdPUTDATA(Ljavacard/framework/APDU;)V {
			.stack 4;
			.locals 6;

			.descriptor	Ljavacard/framework/APDU;	0.10;

				L0:	aload_1;
					invokevirtual 10;		// getBuffer()[B
					astore_2;
					aload_2;
					sconst_2;
					baload;
					ifeq L2;
				L1:	sspush 27392;
					invokestatic 15;		// javacard/framework/ISOException.throwIt(S)V
				L2:	aload_2;
					sconst_3;
					baload;
					sspush 255;
					sand;
					sstore_3;
					sload_3;
					bspush 64;
					if_scmplt L4;
				L3:	sload_3;
					sspush 254;
					if_scmple L5;
				L4:	sspush 27392;
					invokestatic 15;		// javacard/framework/ISOException.throwIt(S)V
				L5:	aload_2;
					sconst_4;
					baload;
					sspush 255;
					sand;
					sstore 4;
					aload_0;
					aload_1;
					invokevirtual 17;		// receiveAPDUBody(Ljavacard/framework/APDU;)V
					getstatic_a 4;		// reference test/TestApplet.pin
					invokevirtual 22;		// isValidated()Z
					ifne L7;
				L6:	sspush 27010;
					invokestatic 15;		// javacard/framework/ISOException.throwIt(S)V
				L7:	aload_0;
					sload 4;
					sload_3;
					aload_1;
					invokevirtual 23;		// SetDO(SSLjavacard/framework/APDU;)S
					sstore 5;
					sload 5;
					bspush 10;
					if_scmpne L9;
				L8:	sspush -28672;
					invokestatic 15;		// javacard/framework/ISOException.throwIt(S)V
					goto L14;
				L9:	sload 5;
					bspush 11;
					if_scmpne L11;
				L10:	sspush 27268;
					invokestatic 15;		// javacard/framework/ISOException.throwIt(S)V
					goto L14;
				L11:	sload 5;
					bspush 12;
					if_scmpne L13;
				L12:	aload_0;
					sload_3;
					invokevirtual 24;		// GetIdxToDO(S)S
					sstore 6;
					getstatic_a 1;		// reference test/TestApplet.memory
					sload 6;
					sconst_1;
					sadd;
					baload;
					sstore 7;
					sspush 26368;
					sload 7;
					sadd;
					invokestatic 15;		// javacard/framework/ISOException.throwIt(S)V
					goto L14;
				L13:	sspush 28416;
					invokestatic 15;		// javacard/framework/ISOException.throwIt(S)V
				L14:	return;
		}

		.method private cmdGETDATA(Ljavacard/framework/APDU;)V {
			.stack 4;
			.locals 5;

			.descriptor	Ljavacard/framework/APDU;	0.10;

				L0:	aload_1;
					invokevirtual 10;		// getBuffer()[B
					astore_2;
					aload_2;
					sconst_2;
					baload;
					ifeq L2;
				L1:	sspush 27392;
					invokestatic 15;		// javacard/framework/ISOException.throwIt(S)V
				L2:	aload_2;
					sconst_3;
					baload;
					sspush 255;
					sand;
					sstore_3;
					sload_3;
					bspush 64;
					if_scmplt L4;
				L3:	sload_3;
					sspush 254;
					if_scmple L5;
				L4:	sspush 27392;
					invokestatic 15;		// javacard/framework/ISOException.throwIt(S)V
				L5:	aload_2;
					sconst_4;
					baload;
					sspush 255;
					sand;
					sstore 4;
					sload 4;
					bspush 9;
					if_scmple L7;
				L6:	sspush 26368;
					invokestatic 15;		// javacard/framework/ISOException.throwIt(S)V
				L7:	aload_0;
					sload_3;
					invokevirtual 24;		// GetIdxToDO(S)S
					sstore 5;
					sload 5;
					bspush 13;
					if_scmpne L9;
				L8:	sspush 27272;
					invokestatic 15;		// javacard/framework/ISOException.throwIt(S)V
				L9:	getstatic_a 1;		// reference test/TestApplet.memory
					sload 5;
					sconst_1;
					sadd;
					baload;
					sstore 6;
					sload 6;
					sstore 6;
					sload 4;
					sload 6;
					if_scmpeq L11;
				L10:	sspush 26368;
					invokestatic 15;		// javacard/framework/ISOException.throwIt(S)V
				L11:	sload 5;
					sconst_1;
					sadd;
					sconst_1;
					sadd;
					sstore 5;
					aload_1;
					invokevirtual 25;		// setOutgoing()S
					pop;
					aload_1;
					sload 4;
					invokevirtual 26;		// setOutgoingLength(S)V
					aload_1;
					getstatic_a 1;		// reference test/TestApplet.memory
					sload 5;
					sload 4;
					invokevirtual 27;		// sendBytesLong([BSS)V
					return;
		}

		.method private cmdDELETE(Ljavacard/framework/APDU;)V {
			.stack 4;
			.locals 2;

			.descriptor	Ljavacard/framework/APDU;	0.10;

				L0:	aload_1;
					invokevirtual 10;		// getBuffer()[B
					astore_2;
					aload_2;
					sconst_2;
					baload;
					ifeq L2;
				L1:	sspush 27392;
					invokestatic 15;		// javacard/framework/ISOException.throwIt(S)V
				L2:	aload_2;
					sconst_3;
					baload;
					ifeq L4;
				L3:	sspush 27392;
					invokestatic 15;		// javacard/framework/ISOException.throwIt(S)V
				L4:	aload_2;
					sconst_4;
					baload;
					sspush 255;
					sand;
					sstore_3;
					sload_3;
					ifeq L6;
				L5:	sspush 26368;
					invokestatic 15;		// javacard/framework/ISOException.throwIt(S)V
				L6:	getstatic_a 4;		// reference test/TestApplet.pin
					invokevirtual 22;		// isValidated()Z
					ifne L8;
				L7:	sspush 27010;
					invokestatic 15;		// javacard/framework/ISOException.throwIt(S)V
				L8:	getstatic_a 1;		// reference test/TestApplet.memory
					sconst_0;
					bspush 9;
					sconst_0;
					invokestatic 28;		// javacard/framework/Util.arrayFillNonAtomic([BSSB)S
					pop;
					sconst_0;
					putstatic_s 29;		// short test/TestApplet.memory_NoOfDOs
					sspush -28672;
					invokestatic 15;		// javacard/framework/ISOException.throwIt(S)V
					return;
		}

		.method public receiveAPDUBody(Ljavacard/framework/APDU;)V 8 {
			.stack 2;
			.locals 2;

			.descriptor	Ljavacard/framework/APDU;	0.10;

				L0:	aload_1;
					invokevirtual 10;		// getBuffer()[B
					astore_2;
					aload_2;
					sconst_4;
					baload;
					sspush 255;
					sand;
					sstore_3;
					sload_3;
					aload_1;
					invokevirtual 30;		// setIncomingAndReceive()S
					if_scmpeq L2;
				L1:	sspush 26368;
					invokestatic 15;		// javacard/framework/ISOException.throwIt(S)V
				L2:	return;
		}

		.method public GetIdxToFreeSpace()S 9 {
			.stack 3;
			.locals 4;

				L0:	sconst_0;
					sstore_3;
					sconst_0;
					sstore 4;
					goto L2;
				L1:	getstatic_a 1;		// reference test/TestApplet.memory
					sload_3;
					baload;
					sstore_1;
					getstatic_a 1;		// reference test/TestApplet.memory
					sload_3;
					sconst_1;
					sadd;
					baload;
					sstore_2;
					sload_3;
					sload_2;
					sadd;
					sconst_1;
					sadd;
					sconst_1;
					sadd;
					sstore_3;
					sinc 4 1;
				L2:	sload 4;
					getstatic_s 29;		// short test/TestApplet.memory_NoOfDOs
					if_scmplt L1;
				L3:	sload_3;
					sreturn;
		}

		.method public GetIdxToDO(S)S 10 {
			.stack 3;
			.locals 4;

				L0:	sconst_0;
					sstore 4;
					sconst_0;
					sstore 5;
					goto L4;
				L1:	getstatic_a 1;		// reference test/TestApplet.memory
					sload 4;
					baload;
					sstore_2;
					sload_2;
					sload_1;
					if_scmpne L3;
				L2:	sload 4;
					sreturn;
				L3:	getstatic_a 1;		// reference test/TestApplet.memory
					sload 4;
					sconst_1;
					sadd;
					baload;
					sstore_3;
					sload 4;
					sload_3;
					sadd;
					sconst_1;
					sadd;
					sconst_1;
					sadd;
					sstore 4;
					sinc 5 1;
				L4:	sload 5;
					getstatic_s 29;		// short test/TestApplet.memory_NoOfDOs
					if_scmplt L1;
				L5:	bspush 13;
					sreturn;
		}

		.method public SetDO(SSLjavacard/framework/APDU;)S 11 {
			.stack 5;
			.locals 5;

			.descriptor	Ljavacard/framework/APDU;	0.10;

				L0:	aload_3;
					invokevirtual 10;		// getBuffer()[B
					astore 4;
					aload_0;
					sload_2;
					invokevirtual 24;		// GetIdxToDO(S)S
					sstore 5;
					sload 5;
					bspush 13;
					if_scmpne L4;
				L1:	aload_0;
					invokevirtual 31;		// GetIdxToFreeSpace()S
					sstore 6;
					bspush 9;
					sload 6;
					ssub;
					sstore 7;
					sload_1;
					sconst_1;
					sadd;
					sconst_1;
					sadd;
					sstore 8;
					sload 8;
					sload 7;
					if_scmpgt L3;
				L2:	getstatic_a 1;		// reference test/TestApplet.memory
					sload 6;
					sload_2;
					s2b;
					bastore;
					getstatic_a 1;		// reference test/TestApplet.memory
					sload 6;
					sconst_1;
					sadd;
					sload_1;
					s2b;
					bastore;
					aload 4;
					sconst_5;
					getstatic_a 1;		// reference test/TestApplet.memory
					sload 6;
					sconst_1;
					sadd;
					sconst_1;
					sadd;
					sload_1;
					invokestatic 32;		// javacard/framework/Util.arrayCopy([BS[BSS)S
					pop;
					getstatic_s 29;		// short test/TestApplet.memory_NoOfDOs
					sconst_1;
					sadd;
					putstatic_s 29;		// short test/TestApplet.memory_NoOfDOs
					bspush 10;
					sreturn;
				L3:	bspush 11;
					sreturn;
				L4:	sload_1;
					getstatic_a 1;		// reference test/TestApplet.memory
					sload 5;
					sconst_1;
					sadd;
					baload;
					if_scmpeq L6;
				L5:	bspush 12;
					sreturn;
				L6:	aload 4;
					sconst_5;
					getstatic_a 1;		// reference test/TestApplet.memory
					sload 5;
					sconst_1;
					sadd;
					sconst_1;
					sadd;
					sload_1;
					invokestatic 32;		// javacard/framework/Util.arrayCopy([BS[BSS)S
					pop;
					bspush 10;
					sreturn;
		}

	}

}
